grobid_tei_xml/__init__.py
grobid_tei_xml/__main__.py
grobid_tei_xml/grobid2json.py
grobid_tei_xml/grobid_unstructured.py
grobid_tei_xml/parse.py
grobid_tei_xml/py.typed
grobid_tei_xml/types.py
grobid_tei_xml-0.1.3.dist-info/LICENSE.txt
grobid_tei_xml-0.1.3.dist-info/METADATA
grobid_tei_xml-0.1.3.dist-info/WHEEL
grobid_tei_xml-0.1.3.dist-info/top_level.txt
grobid_tei_xml-0.1.3.dist-info/RECORD
