Metadata-Version: 2.1
Name: grobid-tei-xml
Version: 0.1.3
Summary: parser and transforms for GROBID-flavor TEI-XML
Home-page: https://gitlab.com/internetarchive/grobid_tei_xml
Author: Bryan Newbold
Author-email: bnewbold@archive.org
License: UNKNOWN
Platform: UNKNOWN
Classifier: Programming Language :: Python :: 3
Classifier: Programming Language :: Python :: 3.7
Classifier: License :: OSI Approved :: MIT License
Classifier: Operating System :: OS Independent
Requires-Python: >=3.7
Provides-Extra: dev
Requires-Dist: isort ; extra == 'dev'
Requires-Dist: mypy ; extra == 'dev'
Requires-Dist: pytest ; extra == 'dev'
Requires-Dist: pytest-codeblocks ; extra == 'dev'
Requires-Dist: pytest-cov ; extra == 'dev'
